src/gates.v
module gates(input a, input b, output x,output y,output z);

  assign x = a & b;
  assign y=a^b;
  assign z=a|b;

endmodule

src/gates.tb.v
`include "gates.v"
module gates_tb();

  // Declare inputs and outputs
  reg a;
  reg b;
  wire x;
  wire y;
  wire z;
  

  gates dut(a, b, x, y, z);


  initial begin
    $dumpfile("gates.vcd");
    $dumpvars(0, gates_tb);
    #5 a = 0;
    #5 b = 0;
 

    for (integer i=0; i<2; i=i+1) begin
        for (integer j=0;j<2;j=j+1) begin
            #10 a=j;
            #10 b=i;
            #10 $display("\n \n Case:%d",i+j);
            #10 $display("AND TEST \n a = %b, b = %b, x = %b", a, b, x);
            #10 $display("XOR TEST \n a = %b, b = %b, y = %b", a, b, y);
            #10 $display("OR TEST \n a = %b, b = %b, z = %b", a, b, z);
        end
    end
    #5 $finish;
  end

endmodule

src/gates.vcd
$date
	Sat Mar  4 21:55:02 2023
$end
$version
	Icarus Verilog
$end
$timescale
	1s
$end
$scope module gates_tb $end
$var wire 1 ! z $end
$var wire 1 " y $end
$var wire 1 # x $end
$var reg 1 $ a $end
$var reg 1 % b $end
$scope module dut $end
$var wire 1 $ a $end
$var wire 1 % b $end
$var wire 1 # x $end
$var wire 1 " y $end
$var wire 1 ! z $end
$upscope $end
$scope begin $ivl_for_loop0 $end
$var integer 32 & i [31:0] $end
$scope begin $ivl_for_loop1 $end
$var integer 32 ' j [31:0] $end
$upscope $end
$upscope $end
$upscope $end
$enddefinitions $end
$comment Show the parameter values. $end
$dumpall
$end
#0
$dumpvars
bx '
bx &
x%
x$
x#
x"
x!
$end
#5
0#
0$
#10
0"
0!
b0 '
b0 &
0%
#70
b1 '
#80
1"
1!
1$
#130
b1 &
b0 '
#140
0"
0!
0$
#150
1"
1!
1%
#190
b1 '
#200
1#
0"
1$
#250
b10 &
b10 '
